slack_archiver.py
wayslack.py
wayslack-0.3.1.dist-info/METADATA
wayslack-0.3.1.dist-info/RECORD
wayslack-0.3.1.dist-info/WHEEL
wayslack-0.3.1.dist-info/entry_points.txt
wayslack-0.3.1.dist-info/pbr.json
wayslack-0.3.1.dist-info/top_level.txt
