Metadata-Version: 2.1
Name: wayslack
Version: 0.3.1
Summary: The Wayslack Machine: incrementally archive Slack messages and files using Slack's team export format
Home-page: https://github.com/wolever/wayslack
Author: David Wolever
Author-email: david@wolever.net
License: BSD
Platform: UNKNOWN
Classifier: Development Status :: 3 - Alpha
Classifier: Environment :: Console
Classifier: License :: OSI Approved :: BSD License
Classifier: Natural Language :: English
Classifier: Operating System :: OS Independent
Classifier: Programming Language :: Python :: 2
Classifier: Topic :: Utilities
Requires-Dist: PyYAML (<4)
Requires-Dist: pathlib (<2)
Requires-Dist: slacker (<1)
Requires-Dist: requests (<3)
